django_ws-1.0.2.dist-info/METADATA
django_ws-1.0.2.dist-info/WHEEL
django_ws-1.0.2.dist-info/licenses/LICENSE
django_ws/__init__.py
django_ws/app.py
django_ws/handler.py
django_ws/version.py
django_ws-1.0.2.dist-info/RECORD
