Metadata-Version: 2.1
Name: django-ws
Version: 1.0.2
Summary: Helpers for using WebSockets in Django
Home-page: https://github.com/pizzapanther/django-ws
Author-Email: Paul Bailey <paul@neutron.studio>
License: BSD 3-Clause
Project-URL: Homepage, https://github.com/pizzapanther/django-ws
Requires-Python: >=3.10
Requires-Dist: websockets>=12.0
